.gitignore
CHANGES.txt
DEVELOPMENT.txt
IDEAS.txt
MANIFEST.in
README.txt
setup.py
docs/LICENSE.GPL
docs/LICENSE.txt
experimental/__init__.py
experimental.catalogqueryplan.egg-info/PKG-INFO
experimental.catalogqueryplan.egg-info/SOURCES.txt
experimental.catalogqueryplan.egg-info/dependency_links.txt
experimental.catalogqueryplan.egg-info/entry_points.txt
experimental.catalogqueryplan.egg-info/namespace_packages.txt
experimental.catalogqueryplan.egg-info/not-zip-safe
experimental.catalogqueryplan.egg-info/requires.txt
experimental.catalogqueryplan.egg-info/top_level.txt
experimental/catalogqueryplan/__init__.py
experimental/catalogqueryplan/browser.py
experimental/catalogqueryplan/catalog.py
experimental/catalogqueryplan/config.py
experimental/catalogqueryplan/configure.zcml
experimental/catalogqueryplan/dateindex.py
experimental/catalogqueryplan/daterangeindex.py
experimental/catalogqueryplan/difference.c
experimental/catalogqueryplan/difference.pyx
experimental/catalogqueryplan/extendedpathindex.py
experimental/catalogqueryplan/intersection.c
experimental/catalogqueryplan/intersection.pyx
experimental/catalogqueryplan/languageindex.py
experimental/catalogqueryplan/lazy.py
experimental/catalogqueryplan/patches.py
experimental/catalogqueryplan/setpatches.py
experimental/catalogqueryplan/unindex.py
experimental/catalogqueryplan/utils.py
experimental/catalogqueryplan/tests/__init__.py
experimental/catalogqueryplan/tests/test_performance.py
experimental/catalogqueryplan/tests/test_plan.py