Metadata-Version: 1.1
Name: experimental.catalogqueryplan
Version: 3.2.8
Summary: Static query optimized with one plan
Home-page: http://www.jarn.com/
Author: Jarn AS
Author-email: info@jarn.com
License: GPL
Keywords: plone catalog search
Platform: UNKNOWN
Classifier: Framework :: Plone
Classifier: Programming Language :: Python
Classifier: Programming Language :: Python :: 2.6
Classifier: Programming Language :: Python :: 2.7
